pawpaw/__init__.py
pawpaw/_type_magic.py
pawpaw/_version.py
pawpaw/errors.py
pawpaw/infix.py
pawpaw/ito.py
pawpaw/span.py
pawpaw/util.py
pawpaw/arborform/__init__.py
pawpaw/arborform/itorator/__init__.py
pawpaw/arborform/itorator/desc.py
pawpaw/arborform/itorator/extract.py
pawpaw/arborform/itorator/filter.py
pawpaw/arborform/itorator/invert.py
pawpaw/arborform/itorator/itorator.py
pawpaw/arborform/itorator/nuco.py
pawpaw/arborform/itorator/reflect.py
pawpaw/arborform/itorator/regex_itorator.py
pawpaw/arborform/itorator/split.py
pawpaw/arborform/itorator/value_func.py
pawpaw/arborform/postorator/__init__.py
pawpaw/arborform/postorator/postorator.py
pawpaw/arborform/postorator/stacked_reduce.py
pawpaw/arborform/postorator/windowed_join.py
pawpaw/nlp/__init__.py
pawpaw/nlp/nlp.py
pawpaw/ontology/__init__.py
pawpaw/ontology/_query.py
pawpaw/ontology/ontology.py
pawpaw/query/__init__.py
pawpaw/query/_query.py
pawpaw/table/__init__.py
pawpaw/table/table.py
pawpaw/table/styles/__init__.py
pawpaw/table/styles/styles.py
pawpaw/visualization/__init__.py
pawpaw/visualization/ascii_box.py
pawpaw/visualization/highlighter.py
pawpaw/visualization/pepo/__init__.py
pawpaw/visualization/pepo/pepo.py
pawpaw/visualization/sgr/__init__.py
pawpaw/visualization/sgr/sgr.py
pawpaw/visualization/sgr/palettes/__init__.py
pawpaw/visualization/sgr/palettes/palettes.py
pawpaw/xml/__init__.py
pawpaw/xml/descriptors.py
pawpaw/xml/xml_helper.py
pawpaw/xml/xml_parser.py
pawpaw-1.0.1.dist-info/METADATA
pawpaw-1.0.1.dist-info/WHEEL
pawpaw-1.0.1.dist-info/licenses/LICENSE
pawpaw-1.0.1.dist-info/RECORD
