Metadata-Version: 2.4
Name: pawpaw
Version: 1.0.1
Summary: High Performance Text Processing & Segmentation Framework
Project-URL: Homepage, https://github.com/rlayers/pawpaw
Project-URL: Bug Tracker, https://github.com/rlayers/pawpaw/issues
Author-email: "Robert L. Ayers" <rlayers@yahoo.com>
License-Expression: MIT
License-File: LICENSE
Keywords: extract-text,hierarchical-text-segmentation,information-extraction,knowledge-graph,nlp,python,text-processing,text-segmentation,xml-parser
Classifier: Development Status :: 3 - Alpha
Classifier: Intended Audience :: Developers
Classifier: License :: OSI Approved :: MIT License
Classifier: Operating System :: OS Independent
Classifier: Programming Language :: Python :: 3.10
Classifier: Programming Language :: Python :: 3.11
Classifier: Topic :: Software Development :: Libraries :: Python Modules
Classifier: Topic :: Text Processing
Requires-Python: >=3.10
Requires-Dist: regex>=2023.8.8
